foal/__init__.py
foal/__main__.py
foal/acronyms.py
foal/cli.py
foal/version.py
foal/data/finance.yaml
foal/data/global.yaml
foal/data/technology.yaml
foal/schema/acronyms.yaml
foal-0.0.2.dist-info/LICENSE
foal-0.0.2.dist-info/METADATA
foal-0.0.2.dist-info/WHEEL
foal-0.0.2.dist-info/entry_points.txt
foal-0.0.2.dist-info/top_level.txt
foal-0.0.2.dist-info/RECORD
