Metadata-Version: 2.1
Name: foal
Version: 0.0.2
Summary: Merge and lookup acronyms from a directory tree of definitions.
Home-page: https://github.com/jumanjihouse/foal.git
Author: Paul Morgan
Author-email: jumanjiman@gmail.com
License: GPLv3+
Keywords: acronyms lookup
Platform: UNKNOWN
Classifier: Development Status :: 3 - Alpha
Classifier: Topic :: Utilities
Classifier: Intended Audience :: End Users/Desktop
Classifier: Environment :: Console
Classifier: License :: OSI Approved :: GNU General Public License v3 or later (GPLv3+)
Classifier: Programming Language :: Python :: 3
Classifier: Programming Language :: Python :: 3.5
Classifier: Programming Language :: Python :: 3.6
Classifier: Programming Language :: Python :: 3.7
Classifier: Programming Language :: Python :: 3.8
Classifier: Programming Language :: Python :: 3 :: Only
Requires-Python: >=3.5, <4
Requires-Dist: identify (<2,>=1.4.18)
Requires-Dist: ruamel.yaml (<1,>=0.16.10)
